Metadata-Version: 1.1
Name: bob.paper.tifs2018-dsu
Version: 1.0.1
Summary: Tools to reproduce the paper "Heterogeneous Face Recognition Using Domain Specific Units"
Home-page: https://gitlab.idiap.ch/bob/bob.paper.tifs2018_dsu
Author: Tiago de Freitas Pereira
Author-email: tiago.pereira@idiap.ch
License: BSD
Keywords: bob,biometric recognition,evaluation
Platform: UNKNOWN
Classifier: Framework :: Bob
Classifier: Development Status :: 3 - Alpha
Classifier: Intended Audience :: Developers
Classifier: License :: OSI Approved :: BSD License
Classifier: Natural Language :: English
Classifier: Programming Language :: Python
Classifier: Topic :: Scientific/Engineering :: Artificial Intelligence
